pytami.py
PyTAMI-0.0.1.dist-info/LICENSE
PyTAMI-0.0.1.dist-info/METADATA
PyTAMI-0.0.1.dist-info/WHEEL
PyTAMI-0.0.1.dist-info/top_level.txt
PyTAMI-0.0.1.dist-info/RECORD
