Metadata-Version: 2.1
Name: PyTAMI
Version: 0.0.1
Summary: Time-Adjusted Market Index Package for Python
Home-page: https://github.com/nefertiti-nft/PyTAMI
Author: José Ribeiro, Luis Duarte, Nefertiti.tech
Author-email: support@nefertiti.tech
License: UNKNOWN
Platform: UNKNOWN
Classifier: Programming Language :: Python :: 3
Classifier: License :: OSI Approved :: MIT License
Classifier: Operating System :: OS Independent
Requires-Python: >=3.6
Requires-Dist: python-dateutil
